{"id": 54665, "slug": "irides-master-of-blocks", "name": "IRiDES: Master of Blocks", "name_original": "IRiDES: Master of Blocks", "description": "<p>IRiDES: Master of Blocks is an Independent developed commercially released videogame developed by Madpeet and the first game by GOAT Store Publishing in 3 years. It is a puzzle game for the Sega Dreamcast and iPhone that combines strategy and action, an easy to pick up and play and hard to master type of puzzler. The biggest inspiration for Irides has been Q Entertainment's Lumines. Upon release both versions of the game were received positively by critics. The game's release date was announced alongside Rush Rush Rally Racing in order to celebrate the 10th Anniversary of the American Dreamcast.</p>", "metacritic": null, "released": "2009-06-26", "tba": false, "updated": "2019-01-09T12:41:06", "background_image": null, "website": "", "rating": 0.0, "rating_top": 0, "added_by_status": {"owned": 2}, "playtime": 0, "achievements_count": 0, "ratings_count": 0, "suggestions_count": 0, "game_series_count": 0, "reviews_count": 0, "platforms": ["Dreamcast"], "developers": ["Madpeet"], "genres": ["Puzzle"], "publishers": ["GOAT Store", "GOAT Store Publishing"], "esrb_rating": null}